rgd_geometry/__init__.py
rgd_geometry/apps.py
rgd_geometry/serializers.py
rgd_geometry/signals.py
rgd_geometry/urls.py
rgd_geometry/views.py
rgd_geometry/admin/__init__.py
rgd_geometry/admin/geometry.py
rgd_geometry/management/commands/rgd_geometry_demo.py
rgd_geometry/migrations/0001_initial.py
rgd_geometry/migrations/0002_alter_geometryarchive_status.py
rgd_geometry/migrations/__init__.py
rgd_geometry/models/__init__.py
rgd_geometry/models/base.py
rgd_geometry/rest/__init__.py
rgd_geometry/rest/viewsets.py
rgd_geometry/tasks/__init__.py
rgd_geometry/tasks/etl.py
rgd_geometry/tasks/jobs.py
rgd_geometry/templates/rgd_geometry/geometry_detail.html
tests/__init__.py
tests/conftest.py
tests/factories.py
tests/manage.py
tests/test_geometry.py
tests/test_permissions.py
tests/test_rest.py
tests/test_project/__init__.py
tests/test_project/settings.py
tests/test_project/urls.py
django_rgd_geometry-0.3.11.dist-info/METADATA
django_rgd_geometry-0.3.11.dist-info/WHEEL
django_rgd_geometry-0.3.11.dist-info/top_level.txt
django_rgd_geometry-0.3.11.dist-info/RECORD
