Metadata-Version: 2.1
Name: django-rgd-geometry
Version: 0.3.11
Summary: UNKNOWN
Home-page: https://github.com/ResonantGeoData/ResonantGeoData
Author: Kitware, Inc.
Author-email: rgd@kitware.com
License: Apache 2.0
Platform: UNKNOWN
Classifier: Development Status :: 3 - Alpha
Classifier: Environment :: Web Environment
Classifier: Framework :: Django :: 3.0
Classifier: Framework :: Django
Classifier: Intended Audience :: Developers
Classifier: License :: OSI Approved :: Apache Software License
Classifier: Operating System :: OS Independent
Classifier: Programming Language :: Python :: 3
Classifier: Programming Language :: Python :: 3.8
Classifier: Programming Language :: Python
Requires-Python: >=3.8
Requires-Dist: django-rgd (==0.3.11)
Provides-Extra: worker
Requires-Dist: shapely ; extra == 'worker'
Requires-Dist: fiona ; extra == 'worker'
